{"id":"bfd6ba8c-9fc2-4970-a04d-ef38fe9e2428","ingredients":[{"amount":1.0,"category":"Fruit et légumes","icon":"/icons/icons8-pomme-de-terre-96.png","name":"basilic thaï "},{"amount":5.0,"name":"feuille de kaffir","unit":""},{"amount":2.0,"name":"blanc de poulet"},{"amount":2.0,"name":"nuoc-mam","unit":"cas"},{"amount":1.0,"name":"courgette"},{"amount":2.0,"name":"cassonade","unit":"cas"},{"amount":4.0,"name":"huile","unit":"cas"},{"amount":2.0,"name":"pâte de curry vert","unit":"cac"},{"amount":250.0,"name":"lait de coco","unit":"ml"}],"name":"Poulet au curry vert","source_url":"https://www.hervecuisine.com/recette/recette-thailandaise-curry-vert-au-poulet/","steps":[]}